borel/__init__.py
borel/stat.py
borel/zu.py
crostab/__init__.py
crostab/aggreg.py
crostab/crit.py
crostab/crostab.py
crostab/infer_dp_type.py
crostab/table.py
crostab/table_spec.py
elprimero/__init__.py
elprimero/eta.py
elprimero/gp.py
veho/__init__.py
veho/dic.py
veho/fun.py
veho/jso.py
veho/mat.py
veho/vec.py
xbrief/__init__.py
xbrief/fm.py
xbrief/mapx.py
xbrief/matx.py
xbrief/strx.py
xbrief/typ.py
xbrief/vecx.py
xbrief/abbrev/__init__.py
xbrief/curt/__init__.py
xbrief/preci/__init__.py
borel-0.0.1.dist-info/LICENSE
borel-0.0.1.dist-info/METADATA
borel-0.0.1.dist-info/WHEEL
borel-0.0.1.dist-info/top_level.txt
borel-0.0.1.dist-info/RECORD
