Metadata-Version: 2.1
Name: borel
Version: 0.0.1
Summary: A math tool-box
Home-page: https://github.com/hoyeungw/
Author: Hoyeung Wong
Author-email: hoyeungw@outlook.com
License: UNKNOWN
Keywords: math,statistics,calculate
Platform: UNKNOWN
Classifier: Programming Language :: Python :: 3
Classifier: Programming Language :: Python :: 3.6
Classifier: Programming Language :: Python :: 3.7
Classifier: License :: OSI Approved :: MIT License
Classifier: Operating System :: OS Independent
